gbtmtpom/__init__.py
gbtmtpom/blocks.py
gbtmtpom/clusters.py
gbtmtpom/gbtmtpom.py
gbtmtpom/plotting.py
gbtmtpom/stats.py
gbtmtpom/data/ames.geojson
gbtm_tpom-0.0.1.dist-info/METADATA
gbtm_tpom-0.0.1.dist-info/WHEEL
gbtm_tpom-0.0.1.dist-info/top_level.txt
gbtm_tpom-0.0.1.dist-info/RECORD
